attolib/__init__.py
attolib/adk.py
attolib/attobase.py
attolib/io.py
attolib/pulses.py
attolib/version.py
attolib/docs/LSGPA_Algorithm.pdf
attolib/expdata/__init__.py
attolib/expdata/expdata.py
attolib/gpa/__init__.py
attolib/gpa/gpa.py
attolib/proof/__init__.py
attolib/proof/proofbase.py
attolib/proof/geneticalgo/__init__.py
attolib/proof/geneticalgo/geneticalgo.py
attolib/proof/iteralgo/__init__.py
attolib/proof/iteralgo/iteralgo.py
attolib-0.0.2.dist-info/LICENSE
attolib-0.0.2.dist-info/METADATA
attolib-0.0.2.dist-info/WHEEL
attolib-0.0.2.dist-info/top_level.txt
attolib-0.0.2.dist-info/RECORD
